{"stats":{"minecraft:mined":{"minecraft:seagrass":1,"minecraft:hay_block":23,"minecraft:gray_bed":1,"minecraft:crafting_table":4,"minecraft:short_grass":1,"minecraft:oak_log":6,"minecraft:bamboo":1,"minecraft:iron_block":2,"minecraft:oak_leaves":2},"minecraft:custom":{"minecraft:time_since_rest":10809,"minecraft:open_enderchest":1,"minecraft:interact_with_furnace":7,"minecraft:sprint_one_cm":120986,"minecraft:damage_taken":396,"minecraft:walk_one_cm":73973,"minecraft:mob_kills":3,"minecraft:inspect_hopper":1,"minecraft:damage_dealt":584,"minecraft:talked_to_villager":2,"minecraft:swim_one_cm":28785,"minecraft:interact_with_crafting_table":8,"minecraft:fly_one_cm":216359,"minecraft:open_chest":42,"minecraft:crouch_one_cm":128,"minecraft:play_time":38705,"minecraft:sneak_time":198,"minecraft:walk_under_water_one_cm":3115,"minecraft:boat_one_cm":63780,"minecraft:jump":961,"minecraft:interact_with_blast_furnace":3,"minecraft:leave_game":1,"minecraft:walk_on_water_one_cm":7507,"minecraft:time_since_death":38705,"minecraft:sleep_in_bed":2,"minecraft:total_world_time":38705,"minecraft:climb_one_cm":669,"minecraft:fall_one_cm":20958},"minecraft:picked_up":{"minecraft:crafting_table":4,"minecraft:oak_log":6,"minecraft:rotten_flesh":1,"minecraft:hay_block":23,"minecraft:iron_block":2,"minecraft:oak_boat":5,"minecraft:bamboo":12,"minecraft:gray_bed":1},"minecraft:crafted":{"minecraft:oak_boat":1,"minecraft:oak_planks":24,"minecraft:crafting_table":1,"minecraft:stick":4,"minecraft:iron_ingot":18,"minecraft:wooden_pickaxe":1,"minecraft:iron_pickaxe":1,"minecraft:bread":64,"minecraft:wheat":207},"minecraft:killed":{"minecraft:zombie":1,"minecraft:spider":2},"minecraft:used":{"minecraft:water_bucket":5,"minecraft:bread":3,"minecraft:stone_pickaxe":2,"minecraft:oak_planks":1,"minecraft:rotten_flesh":1,"minecraft:stone_axe":4,"minecraft:dirt":16,"minecraft:crafting_table":4,"minecraft:mushroom_stew":8,"minecraft:bucket":5,"minecraft:oak_boat":5,"minecraft:tuff":2}},"DataVersion":4189}